spicedmoon/__init__.py
spicedmoon/_version.py
spicedmoon/angular.py
spicedmoon/basics.py
spicedmoon/constants.py
spicedmoon/coordinates.py
spicedmoon/deprecated.py
spicedmoon/geometry.py
spicedmoon/heliac.py
spicedmoon/types.py
spicedmoon/custombody/__init__.py
spicedmoon/custombody/core.py
spicedmoon/custombody/customkernel.py
spicedmoon/custombody/geotic.py
spicedmoon/custombody/preexisting.py
spicedmoon/custombody/selenic.py
spicedmoon-1.1.0.dist-info/licenses/LICENSE
spicedmoon-1.1.0.dist-info/METADATA
spicedmoon-1.1.0.dist-info/WHEEL
spicedmoon-1.1.0.dist-info/top_level.txt
spicedmoon-1.1.0.dist-info/RECORD
