Metadata-Version: 2.4
Name: spicedmoon
Version: 1.1.0
Summary: Calculation of lunar data using NASA's SPICE toolkit
Author-email: Javier Gatón Herguedas <gaton@goa.uva.es>, Ramiro González Catón <ramiro@goa.uva.es>, Stefan Adriaensen <stefan.adriaensen@vito.be>, Juan Carlos Antuña Sánchez <juancarlos.antuna@grasp-earth.com>, Roberto Román Diez <robertor@goa.uva.es>, Carlos Toledano Olmeda <toledano@goa.uva.es>
Maintainer-email: Javier Gatón Herguedas <gaton@goa.uva.es>
License-Expression: LGPL-3.0-only
Project-URL: Homepage, https://github.com/GOA-UVa/spicedmoon
Project-URL: Repository, https://github.com/GOA-UVa/spicedmoon.git
Project-URL: Issues, https://github.com/GOA-UVa/spicedmoon/issues
Classifier: Development Status :: 3 - Alpha
Classifier: Intended Audience :: Science/Research
Classifier: Natural Language :: English
Classifier: Operating System :: OS Independent
Classifier: Programming Language :: Python :: 3
Classifier: Programming Language :: Python :: 3.7
Classifier: Programming Language :: Python :: 3.8
Classifier: Programming Language :: Python :: 3.9
Classifier: Programming Language :: Python :: 3.10
Classifier: Programming Language :: Python :: 3.11
Classifier: Programming Language :: Python :: 3.12
Classifier: Programming Language :: Python :: 3.13
Classifier: Programming Language :: Python :: 3.14
Classifier: Topic :: Scientific/Engineering :: Astronomy
Classifier: Topic :: Scientific/Engineering :: Atmospheric Science
Requires-Python: >=3.7
License-File: LICENSE
Requires-Dist: numpy>=1.21.5
Requires-Dist: spiceypy>=5.0.0
Dynamic: license-file
